{
  "id": "06-03-d2d-mainboard-smoke-closeout-next-family",
  "name": "06-03-d2d-mainboard-smoke-closeout-next-family",
  "title": "D2d mainboard smoke closeout and next-family advisory",
  "description": "Rerun the public mainboard smoke after D2c, record measured manual/validated coverage movement without changing unrelated verdicts, and generate the next-family advisory for the next deterministic slice.",
  "status": "completed",
  "dev_type": null,
  "scope": null,
  "package": null,
  "priority": "P1",
  "creator": "liwenjin",
  "assignee": "codex",
  "createdAt": "2026-06-03",
  "completedAt": "2026-06-03",
  "branch": null,
  "base_branch": "main",
  "worktree_path": null,
  "commit": null,
  "pr_url": null,
  "subtasks": [],
  "children": [],
  "parent": null,
  "relatedFiles": [],
  "notes": "",
  "meta": {}
}